{
    "name": "Scope Of Work",
    "description": "The Scope of Work model defines a structured plan for executing contributor work; it includes deliverables and roadmaps with milestones with each being linked to ownership, progress tracking.",
    "category": "Project Management",
    "publisher": {
        "name": "Powerhouse",
        "url": "https://powerhouse.inc"
    },
    "documentModels": [
        {
            "id": "powerhouse/scopeofwork",
            "name": "ScopeOfWork"
        }
    ],
    "editors": [
        {
            "id": "powerhouse/scope-of-work-editor",
            "name": "Scope Of Work",
            "documentTypes": ["powerhouse/scopeofwork"]
        }
    ],
    "apps": [],
    "subgraphs": [],
    "importScripts": []
}
